data_helper/__init__.py
data_helper/compare_content.py
data_helper/datatypes.py
data_helper/file.py
data_helper/image.py
data_helper/path.py
datas_helper-0.0.2.dist-info/LICENSE.txt
datas_helper-0.0.2.dist-info/METADATA
datas_helper-0.0.2.dist-info/WHEEL
datas_helper-0.0.2.dist-info/top_level.txt
datas_helper-0.0.2.dist-info/RECORD
