Metadata-Version: 2.1
Name: datas-helper
Version: 0.0.2
Summary: Set of support functions when working with some data files
Author-email: Dao Quang Duy <duydaoquang12@gmail.com>
Maintainer-email: Rabiloo Developers <oss@rabiloo.com>
License: The MIT License
Project-URL: Homepage, https://github.com/rabiloo/python-data-helper
Project-URL: Repository, https://github.com/rabiloo/python-data-helper
Project-URL: Bug Tracker, https://github.com/rabiloo/python-data-helper/issues
Keywords: data-helper,json,csv,tar,gzip,opencv,Pillow
Classifier: Programming Language :: Python :: 3
Classifier: License :: OSI Approved :: MIT License
Classifier: Operating System :: OS Independent
Classifier: Development Status :: 2 - Pre-Alpha
Requires-Python: >=3.10
License-File: LICENSE.txt
Provides-Extra: dev
Requires-Dist: black ; extra == 'dev'
Requires-Dist: flake8 ; extra == 'dev'
Requires-Dist: flake8-pyproject ; extra == 'dev'
Requires-Dist: pytest ; extra == 'dev'
Requires-Dist: pytest-asyncio ; extra == 'dev'
Requires-Dist: typing-extensions ; extra == 'dev'
Requires-Dist: isort ; extra == 'dev'
Provides-Extra: image
Requires-Dist: pillow ; extra == 'image'
Requires-Dist: opencv-python-headless ; extra == 'image'
